{"nodes": [{"id": "users_johntaylor_studioprojects_juice_lib_engine_ironsworn_dart", "label": "ironsworn.dart", "file_type": "code", "source_file": "lib/engine/ironsworn.dart", "source_location": null}, {"id": "engine_ironsworn_ironsworn", "label": "Ironsworn", "file_type": "code", "source_file": "lib/engine/ironsworn.dart", "source_location": null}, {"id": "engine_ironsworn_ironswornroll", "label": "IronswornRoll", "file_type": "code", "source_file": "lib/engine/ironsworn.dart", "source_location": null}, {"id": "engine_ironsworn_dice", "label": "dice", "file_type": "code", "source_file": "lib/engine/ironsworn.dart", "source_location": null}, {"id": "dice", "label": "Dice", "file_type": "code", "source_file": null, "source_location": null}, {"id": "engine_ironsworn_total", "label": "total", "file_type": "code", "source_file": "lib/engine/ironsworn.dart", "source_location": null}, {"id": "engine_ironsworn_actiondie", "label": "actionDie", "file_type": "code", "source_file": "lib/engine/ironsworn.dart", "source_location": null}, {"id": "engine_ironsworn_challenge1", "label": "challenge1", "file_type": "code", "source_file": "lib/engine/ironsworn.dart", "source_location": null}, {"id": "engine_ironsworn_challenge2", "label": "challenge2", "file_type": "code", "source_file": "lib/engine/ironsworn.dart", "source_location": null}, {"id": "engine_ironsworn_outcome", "label": "outcome", "file_type": "code", "source_file": "lib/engine/ironsworn.dart", "source_location": null}, {"id": "engine_ironsworn_match", "label": "match", "file_type": "code", "source_file": "lib/engine/ironsworn.dart", "source_location": null}, {"id": "engine_ironsworn_actionroll", "label": "actionRoll", "file_type": "code", "source_file": "lib/engine/ironsworn.dart", "source_location": null}, {"id": "engine_ironsworn_progressroll", "label": "progressRoll", "file_type": "code", "source_file": "lib/engine/ironsworn.dart", "source_location": null}, {"id": "engine_ironsworn_resolve", "label": "_resolve", "file_type": "code", "source_file": "lib/engine/ironsworn.dart", "source_location": null}, {"id": "engine_ironsworn_oracleroll", "label": "oracleRoll", "file_type": "code", "source_file": "lib/engine/ironsworn.dart", "source_location": null}, {"id": "dice_dart", "label": "dice.dart", "file_type": "code", "source_file": null, "source_location": null}], "edges": [{"source": "users_johntaylor_studioprojects_juice_lib_engine_ironsworn_dart", "target": "engine_ironsworn_ironsworn", "relation": "defines", "confidence": "EXTRACTED", "confidence_score": 1.0, "source_file": "lib/engine/ironsworn.dart", "source_location": null, "weight": 1.0}, {"source": "users_johntaylor_studioprojects_juice_lib_engine_ironsworn_dart", "target": "engine_ironsworn_ironswornroll", "relation": "defines", "confidence": "EXTRACTED", "confidence_score": 1.0, "source_file": "lib/engine/ironsworn.dart", "source_location": null, "weight": 1.0}, {"source": "users_johntaylor_studioprojects_juice_lib_engine_ironsworn_dart", "target": "engine_ironsworn_dice", "relation": "defines", "confidence": "EXTRACTED", "confidence_score": 1.0, "source_file": "lib/engine/ironsworn.dart", "source_location": null, "weight": 1.0}, {"source": "users_johntaylor_studioprojects_juice_lib_engine_ironsworn_dart", "target": "dice", "relation": "references", "confidence": "EXTRACTED", "confidence_score": 1.0, "source_file": "lib/engine/ironsworn.dart", "source_location": null, "weight": 1.0, "context": "variable_type"}, {"source": "users_johntaylor_studioprojects_juice_lib_engine_ironsworn_dart", "target": "engine_ironsworn_total", "relation": "defines", "confidence": "EXTRACTED", "confidence_score": 1.0, "source_file": "lib/engine/ironsworn.dart", "source_location": null, "weight": 1.0}, {"source": "users_johntaylor_studioprojects_juice_lib_engine_ironsworn_dart", "target": "engine_ironsworn_actiondie", "relation": "defines", "confidence": "EXTRACTED", "confidence_score": 1.0, "source_file": "lib/engine/ironsworn.dart", "source_location": null, "weight": 1.0}, {"source": "users_johntaylor_studioprojects_juice_lib_engine_ironsworn_dart", "target": "engine_ironsworn_challenge1", "relation": "defines", "confidence": "EXTRACTED", "confidence_score": 1.0, "source_file": "lib/engine/ironsworn.dart", "source_location": null, "weight": 1.0}, {"source": "users_johntaylor_studioprojects_juice_lib_engine_ironsworn_dart", "target": "engine_ironsworn_challenge2", "relation": "defines", "confidence": "EXTRACTED", "confidence_score": 1.0, "source_file": "lib/engine/ironsworn.dart", "source_location": null, "weight": 1.0}, {"source": "users_johntaylor_studioprojects_juice_lib_engine_ironsworn_dart", "target": "engine_ironsworn_outcome", "relation": "defines", "confidence": "EXTRACTED", "confidence_score": 1.0, "source_file": "lib/engine/ironsworn.dart", "source_location": null, "weight": 1.0}, {"source": "users_johntaylor_studioprojects_juice_lib_engine_ironsworn_dart", "target": "engine_ironsworn_match", "relation": "defines", "confidence": "EXTRACTED", "confidence_score": 1.0, "source_file": "lib/engine/ironsworn.dart", "source_location": null, "weight": 1.0}, {"source": "users_johntaylor_studioprojects_juice_lib_engine_ironsworn_dart", "target": "engine_ironsworn_actionroll", "relation": "defines", "confidence": "EXTRACTED", "confidence_score": 1.0, "source_file": "lib/engine/ironsworn.dart", "source_location": null, "weight": 1.0}, {"source": "users_johntaylor_studioprojects_juice_lib_engine_ironsworn_dart", "target": "engine_ironsworn_progressroll", "relation": "defines", "confidence": "EXTRACTED", "confidence_score": 1.0, "source_file": "lib/engine/ironsworn.dart", "source_location": null, "weight": 1.0}, {"source": "users_johntaylor_studioprojects_juice_lib_engine_ironsworn_dart", "target": "engine_ironsworn_resolve", "relation": "defines", "confidence": "EXTRACTED", "confidence_score": 1.0, "source_file": "lib/engine/ironsworn.dart", "source_location": null, "weight": 1.0}, {"source": "users_johntaylor_studioprojects_juice_lib_engine_ironsworn_dart", "target": "engine_ironsworn_oracleroll", "relation": "defines", "confidence": "EXTRACTED", "confidence_score": 1.0, "source_file": "lib/engine/ironsworn.dart", "source_location": null, "weight": 1.0}, {"source": "users_johntaylor_studioprojects_juice_lib_engine_ironsworn_dart", "target": "dice_dart", "relation": "imports", "confidence": "EXTRACTED", "confidence_score": 1.0, "source_file": "lib/engine/ironsworn.dart", "source_location": null, "weight": 1.0}]}