{"nodes": [{"id": "users_johntaylor_studioprojects_juice_lib_features_hexcrawl_screen_dart", "label": "hexcrawl_screen.dart", "file_type": "code", "source_file": "lib/features/hexcrawl_screen.dart", "source_location": null}, {"id": "features_hexcrawl_screen_hexcrawlscreen", "label": "HexcrawlScreen", "file_type": "code", "source_file": "lib/features/hexcrawl_screen.dart", "source_location": null}, {"id": "consumerstatefulwidget", "label": "ConsumerStatefulWidget", "file_type": "code", "source_file": null, "source_location": null}, {"id": "features_hexcrawl_screen_hexcrawlscreenstate", "label": "_HexcrawlScreenState", "file_type": "code", "source_file": "lib/features/hexcrawl_screen.dart", "source_location": null}, {"id": "consumerstate", "label": "ConsumerState", "file_type": "code", "source_file": null, "source_location": null}, {"id": "hexcrawlscreen", "label": "HexcrawlScreen", "file_type": "code", "source_file": null, "source_location": null}, {"id": "journalprovider", "label": "journalProvider", "file_type": "code", "source_file": null, "source_location": null}, {"id": "hexcrawldataprovider", "label": "hexcrawlDataProvider", "file_type": "code", "source_file": null, "source_location": null}, {"id": "features_hexcrawl_screen_dice", "label": "_dice", "file_type": "code", "source_file": "lib/features/hexcrawl_screen.dart", "source_location": null}, {"id": "features_hexcrawl_screen_climate", "label": "_climate", "file_type": "code", "source_file": "lib/features/hexcrawl_screen.dart", "source_location": null}, {"id": "features_hexcrawl_screen_resulttitle", "label": "_resultTitle", "file_type": "code", "source_file": "lib/features/hexcrawl_screen.dart", "source_location": null}, {"id": "features_hexcrawl_screen_resultbody", "label": "_resultBody", "file_type": "code", "source_file": "lib/features/hexcrawl_screen.dart", "source_location": null}, {"id": "features_hexcrawl_screen_createstate", "label": "createState", "file_type": "code", "source_file": "lib/features/hexcrawl_screen.dart", "source_location": null}, {"id": "features_hexcrawl_screen_set", "label": "_set", "file_type": "code", "source_file": "lib/features/hexcrawl_screen.dart", "source_location": null}, {"id": "features_hexcrawl_screen_logtojournal", "label": "_logToJournal", "file_type": "code", "source_file": "lib/features/hexcrawl_screen.dart", "source_location": null}, {"id": "features_hexcrawl_screen_build", "label": "build", "file_type": "code", "source_file": "lib/features/hexcrawl_screen.dart", "source_location": null}, {"id": "dart_math", "label": "dart:math", "file_type": "code", "source_file": null, "source_location": null}, {"id": "package_flutter_material_dart", "label": "package:flutter/material.dart", "file_type": "code", "source_file": null, "source_location": null}, {"id": "package_flutter_riverpod_flutter_riverpod_dart", "label": "package:flutter_riverpod/flutter_riverpod.dart", "file_type": "code", "source_file": null, "source_location": null}, {"id": "engine_dice_dart", "label": "../engine/dice.dart", "file_type": "code", "source_file": null, "source_location": null}, {"id": "engine_hexcrawl_dart", "label": "../engine/hexcrawl.dart", "file_type": "code", "source_file": null, "source_location": null}, {"id": "state_providers_dart", "label": "../state/providers.dart", "file_type": "code", "source_file": null, "source_location": null}], "edges": [{"source": "users_johntaylor_studioprojects_juice_lib_features_hexcrawl_screen_dart", "target": "features_hexcrawl_screen_hexcrawlscreen", "relation": "defines", "confidence": "EXTRACTED", "confidence_score": 1.0, "source_file": "lib/features/hexcrawl_screen.dart", "source_location": null, "weight": 1.0}, {"source": "features_hexcrawl_screen_hexcrawlscreen", "target": "consumerstatefulwidget", "relation": "inherits", "confidence": "EXTRACTED", "confidence_score": 1.0, "source_file": "lib/features/hexcrawl_screen.dart", "source_location": null, "weight": 1.0}, {"source": "users_johntaylor_studioprojects_juice_lib_features_hexcrawl_screen_dart", "target": "features_hexcrawl_screen_hexcrawlscreenstate", "relation": "defines", "confidence": "EXTRACTED", "confidence_score": 1.0, "source_file": "lib/features/hexcrawl_screen.dart", "source_location": null, "weight": 1.0}, {"source": "features_hexcrawl_screen_hexcrawlscreenstate", "target": "consumerstate", "relation": "inherits", "confidence": "EXTRACTED", "confidence_score": 1.0, "source_file": "lib/features/hexcrawl_screen.dart", "source_location": null, "weight": 1.0}, {"source": "features_hexcrawl_screen_hexcrawlscreenstate", "target": "hexcrawlscreen", "relation": "references", "confidence": "EXTRACTED", "confidence_score": 1.0, "source_file": "lib/features/hexcrawl_screen.dart", "source_location": null, "weight": 1.0}, {"source": "features_hexcrawl_screen_hexcrawlscreenstate", "target": "journalprovider", "relation": "references", "confidence": "EXTRACTED", "confidence_score": 1.0, "source_file": "lib/features/hexcrawl_screen.dart", "source_location": null, "weight": 1.0, "context": "riverpod_reference"}, {"source": "features_hexcrawl_screen_hexcrawlscreenstate", "target": "hexcrawldataprovider", "relation": "references", "confidence": "EXTRACTED", "confidence_score": 1.0, "source_file": "lib/features/hexcrawl_screen.dart", "source_location": null, "weight": 1.0, "context": "riverpod_reference"}, {"source": "users_johntaylor_studioprojects_juice_lib_features_hexcrawl_screen_dart", "target": "features_hexcrawl_screen_dice", "relation": "defines", "confidence": "EXTRACTED", "confidence_score": 1.0, "source_file": "lib/features/hexcrawl_screen.dart", "source_location": null, "weight": 1.0}, {"source": "users_johntaylor_studioprojects_juice_lib_features_hexcrawl_screen_dart", "target": "features_hexcrawl_screen_climate", "relation": "defines", "confidence": "EXTRACTED", "confidence_score": 1.0, "source_file": "lib/features/hexcrawl_screen.dart", "source_location": null, "weight": 1.0}, {"source": "users_johntaylor_studioprojects_juice_lib_features_hexcrawl_screen_dart", "target": "features_hexcrawl_screen_resulttitle", "relation": "defines", "confidence": "EXTRACTED", "confidence_score": 1.0, "source_file": "lib/features/hexcrawl_screen.dart", "source_location": null, "weight": 1.0}, {"source": "users_johntaylor_studioprojects_juice_lib_features_hexcrawl_screen_dart", "target": "features_hexcrawl_screen_resultbody", "relation": "defines", "confidence": "EXTRACTED", "confidence_score": 1.0, "source_file": "lib/features/hexcrawl_screen.dart", "source_location": null, "weight": 1.0}, {"source": "users_johntaylor_studioprojects_juice_lib_features_hexcrawl_screen_dart", "target": "features_hexcrawl_screen_createstate", "relation": "defines", "confidence": "EXTRACTED", "confidence_score": 1.0, "source_file": "lib/features/hexcrawl_screen.dart", "source_location": null, "weight": 1.0}, {"source": "users_johntaylor_studioprojects_juice_lib_features_hexcrawl_screen_dart", "target": "features_hexcrawl_screen_set", "relation": "defines", "confidence": "EXTRACTED", "confidence_score": 1.0, "source_file": "lib/features/hexcrawl_screen.dart", "source_location": null, "weight": 1.0}, {"source": "users_johntaylor_studioprojects_juice_lib_features_hexcrawl_screen_dart", "target": "features_hexcrawl_screen_logtojournal", "relation": "defines", "confidence": "EXTRACTED", "confidence_score": 1.0, "source_file": "lib/features/hexcrawl_screen.dart", "source_location": null, "weight": 1.0}, {"source": "features_hexcrawl_screen_logtojournal", "target": "journalprovider", "relation": "references", "confidence": "EXTRACTED", "confidence_score": 1.0, "source_file": "lib/features/hexcrawl_screen.dart", "source_location": null, "weight": 1.0, "context": "riverpod_reference"}, {"source": "users_johntaylor_studioprojects_juice_lib_features_hexcrawl_screen_dart", "target": "features_hexcrawl_screen_build", "relation": "defines", "confidence": "EXTRACTED", "confidence_score": 1.0, "source_file": "lib/features/hexcrawl_screen.dart", "source_location": null, "weight": 1.0}, {"source": "features_hexcrawl_screen_build", "target": "hexcrawldataprovider", "relation": "references", "confidence": "EXTRACTED", "confidence_score": 1.0, "source_file": "lib/features/hexcrawl_screen.dart", "source_location": null, "weight": 1.0, "context": "riverpod_reference"}, {"source": "users_johntaylor_studioprojects_juice_lib_features_hexcrawl_screen_dart", "target": "dart_math", "relation": "imports", "confidence": "EXTRACTED", "confidence_score": 1.0, "source_file": "lib/features/hexcrawl_screen.dart", "source_location": null, "weight": 1.0}, {"source": "users_johntaylor_studioprojects_juice_lib_features_hexcrawl_screen_dart", "target": "package_flutter_material_dart", "relation": "imports", "confidence": "EXTRACTED", "confidence_score": 1.0, "source_file": "lib/features/hexcrawl_screen.dart", "source_location": null, "weight": 1.0}, {"source": "users_johntaylor_studioprojects_juice_lib_features_hexcrawl_screen_dart", "target": "package_flutter_riverpod_flutter_riverpod_dart", "relation": "imports", "confidence": "EXTRACTED", "confidence_score": 1.0, "source_file": "lib/features/hexcrawl_screen.dart", "source_location": null, "weight": 1.0}, {"source": "users_johntaylor_studioprojects_juice_lib_features_hexcrawl_screen_dart", "target": "engine_dice_dart", "relation": "imports", "confidence": "EXTRACTED", "confidence_score": 1.0, "source_file": "lib/features/hexcrawl_screen.dart", "source_location": null, "weight": 1.0}, {"source": "users_johntaylor_studioprojects_juice_lib_features_hexcrawl_screen_dart", "target": "engine_hexcrawl_dart", "relation": "imports", "confidence": "EXTRACTED", "confidence_score": 1.0, "source_file": "lib/features/hexcrawl_screen.dart", "source_location": null, "weight": 1.0}, {"source": "users_johntaylor_studioprojects_juice_lib_features_hexcrawl_screen_dart", "target": "state_providers_dart", "relation": "imports", "confidence": "EXTRACTED", "confidence_score": 1.0, "source_file": "lib/features/hexcrawl_screen.dart", "source_location": null, "weight": 1.0}]}